<?xml version="1.0" encoding="UTF-8" ?>

<container xmlns="http://symfony.com/schema/dic/services" xmlns:xsi="http://www.w3.org/2001/XMLSchema-instance" xsi:schemaLocation="http://symfony.com/schema/dic/services http://symfony.com/schema/dic/services/services-1.0.xsd">
    <services>
        <service id="Sulu\SyliusProducerPlugin\Producer\Serializer\ProductSerializerInterface"
                 class="Sulu\SyliusProducerPlugin\Producer\Serializer\ProductSerializer">
            <argument type="service" id="jms_serializer"/>
        </service>

        <service id="Sulu\SyliusProducerPlugin\Producer\ProductMessageProducerInterface"
                 class="Sulu\SyliusProducerPlugin\Producer\ProductMessageProducer">
            <argument type="service" id="Sulu\SyliusProducerPlugin\Producer\Serializer\ProductSerializerInterface"/>
            <argument type="service" id="messenger.bus.default"/>
        </service>

        <service id="Sulu\SyliusProducerPlugin\Producer\ProductVariantMessageProducerInterface"
                 class="Sulu\SyliusProducerPlugin\Producer\ProductVariantMessageProducer">
            <argument type="service" id="jms_serializer"/>
            <argument type="service" id="messenger.bus.default"/>
        </service>

        <service id="Sulu\SyliusProducerPlugin\Producer\TaxonMessageProducerInterface"
                 class="Sulu\SyliusProducerPlugin\Producer\TaxonMessageProducer">
            <argument type="service" id="jms_serializer"/>
            <argument type="service" id="messenger.bus.default"/>
        </service>

        <service id="Sulu\SyliusProducerPlugin\EventSubscriber\ProductEventSubscriber">
            <argument type="service" id="Sulu\SyliusProducerPlugin\Producer\ProductMessageProducerInterface"/>

            <tag name="kernel.event_subscriber"/>
        </service>

        <service id="Sulu\SyliusProducerPlugin\EventSubscriber\ProductVariantEventSubscriber">
            <argument type="service" id="Sulu\SyliusProducerPlugin\Producer\ProductVariantMessageProducerInterface"/>

            <tag name="kernel.event_subscriber"/>
        </service>

        <service id="Sulu\SyliusProducerPlugin\EventSubscriber\TaxonEventSubscriber">
            <argument type="service" id="Sulu\SyliusProducerPlugin\Producer\TaxonMessageProducerInterface"/>

            <tag name="kernel.event_subscriber"/>
        </service>

        <service id="Sulu\SyliusProducerPlugin\EventSubscriber\CustomerEventSubscriber">
            <argument type="service" id="sylius.shop_user.token_generator.email_verification" />

            <tag name="kernel.event_subscriber"/>
        </service>

        <service id="Sulu\SyliusProducerPlugin\EventSubscriber\CustomDataSerializeEventSubscriber">
            <tag name="jms_serializer.event_subscriber"/>
        </service>

        <service id="Sulu\SyliusProducerPlugin\EventSubscriber\UserSerializeEventSubscriber">
            <tag name="jms_serializer.event_subscriber"/>
        </service>

        <service id="Sulu\SyliusProducerPlugin\Controller\AuthenticationController">
            <argument type="service" id="jms_serializer"/>
            <argument type="service" id="security.authentication.provider.dao.shop"/>

            <tag name="controller.service_arguments" />
        </service>

        <service id="Sulu\SyliusProducerPlugin\Controller\VerifyController">
            <argument type="service" id="doctrine.orm.entity_manager"/>
            <argument type="service" id="jms_serializer.serializer"/>
            <argument type="service" id="sylius.repository.shop_user"/>

            <tag name="controller.service_arguments" />
        </service>

        <service id="Sulu\SyliusProducerPlugin\Command\SynchronizeTaxonCommand">
            <argument type="service" id="doctrine.orm.entity_manager"/>
            <argument type="service" id="Sulu\SyliusProducerPlugin\Producer\TaxonMessageProducerInterface"/>
            <argument type="service" id="sylius.repository.taxon"/>

            <tag name="console.command" />
        </service>

        <service id="Sulu\SyliusProducerPlugin\Command\SynchronizeProductsCommand">
            <argument type="service" id="doctrine.orm.entity_manager"/>
            <argument type="service" id="Sulu\SyliusProducerPlugin\Producer\ProductMessageProducerInterface"/>
            <argument type="service" id="sylius.repository.product"/>

            <tag name="console.command" />
        </service>

        <service id="Sulu\SyliusProducerPlugin\Command\SynchronizeProductVariantsCommand">
            <argument type="service" id="doctrine.orm.entity_manager"/>
            <argument type="service" id="Sulu\SyliusProducerPlugin\Producer\ProductVariantMessageProducerInterface"/>
            <argument type="service" id="sylius.repository.product_variant"/>

            <tag name="console.command" />
        </service>

        <service id="Sulu\SyliusProducerPlugin\Form\Extension\AddressTypeExtension">
            <tag name="form.type_extension" />
        </service>
    </services>
</container>
